README.rst
ripple_federation.py
setup.py
ripple_federation.egg-info/PKG-INFO
ripple_federation.egg-info/SOURCES.txt
ripple_federation.egg-info/dependency_links.txt
ripple_federation.egg-info/top_level.txt
ripple_federation.egg-info/zip-safe