Metadata-Version: 1.1
Name: ripple-federation
Version: 1.1.5
Summary: Map email to Ripple addresses using the Federation protocol
Home-page: https://github.com/miracle2k/ripple-federation-python
Author: Michael Elsdörfer
Author-email: michael@elsdoerfer.com
License: BSD
Platform: UNKNOWN
Classifier: Development Status :: 5 - Production/Stable
Classifier: Environment :: Web Environment
Classifier: License :: OSI Approved :: BSD License
